grandlight/__init__.py
grandlight/components.py
grandlight/core.py
grandlight/effects.py
grandlight/window.py
grandlight-0.1.1.dist-info/licenses/LICENSE
grandlight-0.1.1.dist-info/METADATA
grandlight-0.1.1.dist-info/WHEEL
grandlight-0.1.1.dist-info/top_level.txt
grandlight-0.1.1.dist-info/RECORD
