Metadata-Version: 2.4
Name: grandlight
Version: 0.1.1
Summary: A modern GUI library featuring glassmorphism design aesthetics
Author-email: Rheehose <contact@rheecreative.com>
Maintainer-email: Rhee Creative <contact@rheecreative.com>
License: MIT
Project-URL: Homepage, https://github.com/hslcrb/grandlight
Project-URL: Documentation, https://github.com/hslcrb/grandlight#readme
Project-URL: Repository, https://github.com/hslcrb/grandlight
Project-URL: Bug Tracker, https://github.com/hslcrb/grandlight/issues
Keywords: gui,glassmorphism,ui,modern,design,graphics
Classifier: Development Status :: 3 - Alpha
Classifier: Intended Audience :: Developers
Classifier: License :: OSI Approved :: MIT License
Classifier: Operating System :: OS Independent
Classifier: Programming Language :: Python :: 3
Classifier: Programming Language :: Python :: 3.8
Classifier: Programming Language :: Python :: 3.9
Classifier: Programming Language :: Python :: 3.10
Classifier: Programming Language :: Python :: 3.11
Classifier: Programming Language :: Python :: 3.12
Classifier: Topic :: Software Development :: Libraries :: Python Modules
Classifier: Topic :: Software Development :: User Interfaces
Requires-Python: >=3.8
License-File: LICENSE
Requires-Dist: pillow>=9.0.0
Requires-Dist: numpy>=1.20.0
Provides-Extra: dev
Requires-Dist: pytest>=7.0.0; extra == "dev"
Requires-Dist: black>=22.0.0; extra == "dev"
Requires-Dist: flake8>=4.0.0; extra == "dev"
Requires-Dist: mypy>=0.950; extra == "dev"
Dynamic: license-file
